{"cameraMode":{"drawMode":0,"name":"Shaded","section":"Shading Mode"},"sceneLighting":true,"audioPlay":false,"sceneViewState":{"m_AlwaysRefresh":false,"showFog":true,"showSkybox":true,"showFlares":true,"showImageEffects":true,"showParticleSystems":true,"showVisualEffectGraphs":true,"m_FxEnabled":true},"in2DMode":false,"pivot":{"x":-1.3225282430648804,"y":-4.6550750732421879,"z":-7.291162014007568},"rotation":{"x":-0.07766247540712357,"y":0.9210297465324402,"z":-0.29433318972587588,"w":-0.2430596649646759},"size":12.124356269836426,"orthographic":false}